xj_finance/__init__.py
xj_finance/admin.py
xj_finance/apps.py
xj_finance/models.py
xj_finance/search_indexes.py
xj_finance/service_register.py
xj_finance/tests.py
xj_finance/urls.py
xj_finance/views.py
xj_finance/apis/__init__.py
xj_finance/apis/finance_apis.py
xj_finance/apis/finance_balance.py
xj_finance/apis/finance_contact_book.py
xj_finance/apis/finance_currency.py
xj_finance/apis/finance_currency_apis.py
xj_finance/apis/finance_export.py
xj_finance/apis/finance_labor_apis.py
xj_finance/apis/finance_ledger_apis.py
xj_finance/apis/finance_opposite_account_apis.py
xj_finance/apis/finance_pay_mode.py
xj_finance/apis/finance_pay_mode_apis.py
xj_finance/apis/finance_payment_type.py
xj_finance/apis/finance_sand_box.py
xj_finance/apis/finance_sand_box_apis.py
xj_finance/apis/finance_statistic.py
xj_finance/apis/finance_status_code.py
xj_finance/apis/finance_status_code_apis.py
xj_finance/apis/finance_transact.py
xj_finance/apis/finance_transacts.py
xj_finance/apis/middleware.py
xj_finance/apis/router.py
xj_finance/management/__init__.py
xj_finance/management/commands/__init__.py
xj_finance/management/commands/finance_test.py
xj_finance/services/__init__.py
xj_finance/services/finance_currency_service.py
xj_finance/services/finance_extend_service.py
xj_finance/services/finance_labor_service.py
xj_finance/services/finance_ledger.py
xj_finance/services/finance_ledger_v1.py
xj_finance/services/finance_ledger_v2.py
xj_finance/services/finance_list_service.py
xj_finance/services/finance_opposite_account_service.py
xj_finance/services/finance_pay_mode_service.py
xj_finance/services/finance_payment_type_service.py
xj_finance/services/finance_sand_box_service.py
xj_finance/services/finance_service v1.py
xj_finance/services/finance_service.py
xj_finance/services/finance_statistic_service.py
xj_finance/services/finance_status_code_service.py
xj_finance/services/finance_transact_service v1.py
xj_finance/services/finance_transact_service v2.py
xj_finance-1.1.55.dist-info/METADATA
xj_finance-1.1.55.dist-info/WHEEL
xj_finance-1.1.55.dist-info/top_level.txt
xj_finance-1.1.55.dist-info/RECORD
