Metadata-Version: 2.1
Name: xj-finance
Version: 1.1.55
Summary: 资金模块
Author: 赵向明
Author-email: sieyoo@163.com
Maintainer: ['莫小瑛', '高栋天']
Maintainer-email: angelvy@foxmail.com
License: apache 3.0
